mechaphlowers-0.5.2.dist-info/METADATA
mechaphlowers-0.5.2.dist-info/WHEEL
mechaphlowers-0.5.2.dist-info/entry_points.txt
mechaphlowers-0.5.2.dist-info/licenses/LICENSE
mechaphlowers/__init__.py
mechaphlowers/api/__init__.py
mechaphlowers/api/frames.py
mechaphlowers/api/state.py
mechaphlowers/config.py
mechaphlowers/core/__init__.py
mechaphlowers/core/geometry/__init__.py
mechaphlowers/core/geometry/line_angles.py
mechaphlowers/core/geometry/points.py
mechaphlowers/core/geometry/references.py
mechaphlowers/core/geometry/rotation.py
mechaphlowers/core/models/__init__.py
mechaphlowers/core/models/balance/__init__.py
mechaphlowers/core/models/balance/engine.py
mechaphlowers/core/models/balance/interfaces.py
mechaphlowers/core/models/balance/models/__init__.py
mechaphlowers/core/models/balance/models/model_ducloux.py
mechaphlowers/core/models/balance/models/utils_model_ducloux.py
mechaphlowers/core/models/balance/solvers/__init__.py
mechaphlowers/core/models/balance/solvers/balance_solver.py
mechaphlowers/core/models/balance/solvers/find_parameter_solver.py
mechaphlowers/core/models/cable/__init__.py
mechaphlowers/core/models/cable/deformation.py
mechaphlowers/core/models/cable/span.py
mechaphlowers/core/models/external_loads.py
mechaphlowers/core/papoto/__init__.py
mechaphlowers/core/papoto/papoto_model.py
mechaphlowers/core/solver/__init__.py
mechaphlowers/core/solver/cable_state.py
mechaphlowers/data/__init__.py
mechaphlowers/data/catalog/__init__.py
mechaphlowers/data/catalog/catalog.py
mechaphlowers/data/catalog/iris_dataset.csv
mechaphlowers/data/catalog/pokemon.csv
mechaphlowers/data/catalog/pokemon.yaml
mechaphlowers/data/catalog/sample_cable_database.csv
mechaphlowers/data/catalog/sample_cable_database.yaml
mechaphlowers/data/catalog/sample_pylon_database.csv
mechaphlowers/data/catalog/sample_pylon_database.yaml
mechaphlowers/data/catalog/sample_section.py
mechaphlowers/data/geography/__init__.py
mechaphlowers/data/geography/elevation.py
mechaphlowers/data/geography/example_supports_gps_points.json
mechaphlowers/data/geography/helpers.py
mechaphlowers/data/initializer/__init__.py
mechaphlowers-0.5.2.dist-info/RECORD
