Metadata-Version: 2.1
Name: mechaphlowers
Version: 0.5.2
Summary: Physical calculation package for the mechanics and geometry of power lines
Author: Adrien Goeller, Jeremy Wang
Classifier: Development Status :: 3 - Alpha
Classifier: Intended Audience :: Science/Research
Classifier: Intended Audience :: Developers
Classifier: License :: OSI Approved :: Mozilla Public License 2.0 (MPL 2.0)
Classifier: Natural Language :: English
Classifier: Programming Language :: Python :: 3 :: Only
Classifier: Programming Language :: Python :: 3.11
Classifier: Programming Language :: Python :: 3.12
Classifier: Programming Language :: Python :: 3.13
Classifier: Operating System :: OS Independent
Project-URL: Homepage, https://github.com/phlowers/mechaphlowers
Project-URL: Issues, https://github.com/phlowers/mechaphlowers/issues
Project-URL: Documentation, https://phlowers.readthedocs.io/projects/mechaphlowers/
Requires-Python: <3.14,>=3.11
Requires-Dist: numpy==2.2.5
Requires-Dist: pandas==2.3.1
Requires-Dist: pandera<=0.23.1
Requires-Dist: plotly<=5.24.1
Requires-Dist: pyyaml==6.0.2
Requires-Dist: pint==0.25
Requires-Dist: xxhash==3.5.0
Requires-Dist: pydantic==2.10.6
Provides-Extra: full
Requires-Dist: scipy<=1.14.1; extra == "full"
Requires-Dist: requests==2.32.4; extra == "full"
